vault_certificate_deploy/__init__.py
vault_certificate_deploy/base/__init__.py
vault_certificate_deploy/colors/__init__.py
vault_certificate_deploy-1.4.2.data/scripts/vault-certificate-deploy
vault_certificate_deploy-1.4.2.data/scripts/vault-certificate-issue-deploy
vault_certificate_deploy-1.4.2.dist-info/LICENSE
vault_certificate_deploy-1.4.2.dist-info/METADATA
vault_certificate_deploy-1.4.2.dist-info/WHEEL
vault_certificate_deploy-1.4.2.dist-info/top_level.txt
vault_certificate_deploy-1.4.2.dist-info/RECORD
