Metadata-Version: 2.1
Name: vault-certificate-deploy
Version: 1.4.2
Summary: System for deploying certificates from Hashicorp Vault server
Home-page: https://github.com/rvojcik/vault-certificate-deploy
Author: Robert Vojcik
Author-email: robert@vojcik.net
License: GPLv3
Keywords: vault_certificate_deploy,vault_cert_deploy,certificate,vault-certificate-deploy,vault-cert-deploy,hashicorp,certificates
Classifier: License :: OSI Approved :: GNU General Public License v3 (GPLv3)
Classifier: Operating System :: POSIX
Classifier: Operating System :: Unix
Classifier: Operating System :: POSIX :: Linux
Classifier: Programming Language :: Python
Classifier: Programming Language :: Python :: 3
Classifier: Programming Language :: Python :: 3.6
Classifier: Programming Language :: Python :: 3.7
Classifier: Programming Language :: Python :: 3.8
Classifier: Programming Language :: Python :: 3.9
Classifier: Programming Language :: Python :: 3.10
Classifier: Programming Language :: Python :: 3.11
Classifier: Topic :: System :: Systems Administration
Classifier: Topic :: Database
Classifier: Topic :: Security
Classifier: Topic :: Security :: Cryptography
License-File: LICENSE
Requires-Dist: urllib3
Requires-Dist: hvac <0.11.0,>=0.10.1
Requires-Dist: requests >=2.1
Requires-Dist: configparser
Requires-Dist: pyOpenSSL >=17.0
